handbrake_batch_compressor/__init__.py
handbrake_batch_compressor/main.py
handbrake_batch_compressor/src/__init__.py
handbrake_batch_compressor/src/cli/__init__.py
handbrake_batch_compressor/src/cli/cli_guards.py
handbrake_batch_compressor/src/cli/guide.py
handbrake_batch_compressor/src/cli/handbrake_cli_output_capturer.py
handbrake_batch_compressor/src/cli/logger.py
handbrake_batch_compressor/src/cli/statistics_logger.py
handbrake_batch_compressor/src/compression/__init__.py
handbrake_batch_compressor/src/compression/compression_manager.py
handbrake_batch_compressor/src/compression/compression_statistics.py
handbrake_batch_compressor/src/compression/handbrake_compressor.py
handbrake_batch_compressor/src/errors/__init__.py
handbrake_batch_compressor/src/errors/cancel_compression_by_user.py
handbrake_batch_compressor/src/errors/handbrake_cli_exceptions.py
handbrake_batch_compressor/src/utils/__init__.py
handbrake_batch_compressor/src/utils/ffmpeg_helpers.py
handbrake_batch_compressor/src/utils/files.py
handbrake_batch_compressor/src/utils/smart_filters.py
handbrake_batch_compressor/src/utils/third_party_installers.py
handbrake_batch_compressor-3.0.0.dist-info/LICENSE
handbrake_batch_compressor-3.0.0.dist-info/METADATA
handbrake_batch_compressor-3.0.0.dist-info/WHEEL
handbrake_batch_compressor-3.0.0.dist-info/entry_points.txt
handbrake_batch_compressor-3.0.0.dist-info/RECORD
