Metadata-Version: 2.3
Name: handbrake-batch-compressor
Version: 3.0.0
Summary: Simple script to traverse all the video files and compress them to optimize disk space for large files
Author: Roman Berezkin
Author-email: Glitchy-Sheep@users.noreply.github.com
Requires-Python: >=3.10,<3.14
Classifier: Programming Language :: Python :: 3
Classifier: Programming Language :: Python :: 3.10
Classifier: Programming Language :: Python :: 3.11
Classifier: Programming Language :: Python :: 3.12
Classifier: Programming Language :: Python :: 3.13
Requires-Dist: aiofiles (>=24.1.0,<25.0.0)
Requires-Dist: av (>=14.1.0,<15.0.0)
Requires-Dist: numpy (>=2.2.2,<3.0.0)
Requires-Dist: pydantic (>=2.10.6,<3.0.0)
Requires-Dist: typer (>=0.15.1,<0.16.0)
